{
  "main": {
    "id": "35a7aa9361ece0c1",
    "type": "split",
    "children": [
      {
        "id": "25b17863dcac7a15",
        "type": "tabs",
        "children": [
          {
            "id": "60e428461f01bf3d",
            "type": "leaf",
            "state": {
              "type": "markdown",
              "state": {
                "file": "202407271841.md",
                "mode": "source",
                "source": false
              }
            }
          }
        ]
      },
      {
        "id": "e18836fd6a2288c5",
        "type": "tabs",
        "children": [
          {
            "id": "881946b426ec307c",
            "type": "leaf",
            "state": {
              "type": "markdown",
              "state": {
                "file": "Services.md",
                "mode": "source",
                "source": false
              }
            }
          }
        ]
      }
    ],
    "direction": "vertical"
  },
  "left": {
    "id": "543643ffbad5876b",
    "type": "split",
    "children": [
      {
        "id": "896982fa3e71578c",
        "type": "tabs",
        "children": [
          {
            "id": "073599c6ed2594e8",
            "type": "leaf",
            "state": {
              "type": "file-explorer",
              "state": {
                "sortOrder": "alphabetical"
              }
            }
          },
          {
            "id": "b16bcd200299077c",
            "type": "leaf",
            "state": {
              "type": "search",
              "state": {
                "query": "",
                "matchingCase": false,
                "explainSearch": false,
                "collapseAll": false,
                "extraContext": false,
                "sortOrder": "alphabetical"
              }
            }
          },
          {
            "id": "ea1034720d8dfa73",
            "type": "leaf",
            "state": {
              "type": "bookmarks",
              "state": {}
            }
          }
        ]
      }
    ],
    "direction": "horizontal",
    "width": 300
  },
  "right": {
    "id": "cca6fecb96904b97",
    "type": "split",
    "children": [
      {
        "id": "bad41ca48e13d323",
        "type": "tabs",
        "children": [
          {
            "id": "3cecf303dcf5f551",
            "type": "leaf",
            "state": {
              "type": "backlink",
              "state": {
                "file": "202407271841.md",
                "collapseAll": false,
                "extraContext": false,
                "sortOrder": "alphabetical",
                "showSearch": false,
                "searchQuery": "",
                "backlinkCollapsed": false,
                "unlinkedCollapsed": true
              }
            }
          },
          {
            "id": "e0d92951f2fcd43d",
            "type": "leaf",
            "state": {
              "type": "outgoing-link",
              "state": {
                "file": "202407271841.md",
                "linksCollapsed": false,
                "unlinkedCollapsed": true
              }
            }
          },
          {
            "id": "0e9013a815006093",
            "type": "leaf",
            "state": {
              "type": "tag",
              "state": {
                "sortOrder": "frequency",
                "useHierarchy": true
              }
            }
          },
          {
            "id": "d1009a12b72043f7",
            "type": "leaf",
            "state": {
              "type": "outline",
              "state": {
                "file": "202407271841.md"
              }
            }
          }
        ]
      }
    ],
    "direction": "horizontal",
    "width": 300,
    "collapsed": true
  },
  "left-ribbon": {
    "hiddenItems": {
      "switcher:Open quick switcher": false,
      "graph:Open graph view": false,
      "canvas:Create new canvas": false,
      "daily-notes:Open today's daily note": false,
      "templates:Insert template": false,
      "command-palette:Open command palette": false,
      "workspaces:Manage workspace layouts": false,
      "zk-prefixer:Create new unique note": false
    }
  },
  "active": "073599c6ed2594e8",
  "lastOpenFiles": [
    "Operation Duckman.md",
    "202407271841.md",
    "202407260052.md",
    "Services.md"
  ]
}